Flask_Collect-1.3.2.dist-info/DESCRIPTION.rst
Flask_Collect-1.3.2.dist-info/METADATA
Flask_Collect-1.3.2.dist-info/RECORD
Flask_Collect-1.3.2.dist-info/WHEEL
Flask_Collect-1.3.2.dist-info/metadata.json
Flask_Collect-1.3.2.dist-info/top_level.txt
flask_collect/__init__.py
flask_collect/collect.py
flask_collect/storage/__init__.py
flask_collect/storage/base.py
flask_collect/storage/file.py
flask_collect/storage/link.py
flask_collect/storage/test.py
tests/__init__.py
tests/test_collect.py
