Metadata-Version: 2.0
Name: Flask-Collect
Version: 1.3.2
Summary: Flask-Collect -- Collect static files in Flask application
Requires-Dist: flask (>=0.10.1)
